Workbook

Sheet Recettes et dépenses
A1: REFEM — Rapport financier du 1er semestre 2026
A2: Montants en francs guinéens (GNF). Document fictif — données de démonstration AssoHub
A4: Solde de trésorerie au 1er janvier 2026 | B4: 5040000
A6: Poste | B6: Janv. | C6: Févr. | D6: Mars | E6: Avr. | F6: Mai | G6: Juin | H6: Total S1
A7: RECETTES
A8: Cotisations mensuelles | B8: 1350000 | C8: 1500000 | D8: 1550000 | E8: 1500000 | F8: 1600000 | G8: 1600000 | H8: =SUM(B8:G8) -> 9100000
A9: Droits d'adhésion | B9: 200000 | C9: 100000 | D9: 0 | E9: 100000 | F9: 200000 | G9: 100000 | H9: =SUM(B9:G9) -> 700000
A10: Total recettes | B10: =SUM(B8:B9) -> 1550000 | C10: =SUM(C8:C9) -> 1600000 | D10: =SUM(D8:D9) -> 1550000 | E10: =SUM(E8:E9) -> 1600000 | F10: =SUM(F8:F9) -> 1800000 | G10: =SUM(G8:G9) -> 1700000 | H10: =SUM(H8:H9) -> 9800000
A12: DÉPENSES
A13: Location de salle | B13: 750000 | C13: 0 | D13: 0 | E13: 0 | F13: 0 | G13: 0 | H13: =SUM(B13:G13) -> 750000
A14: Collations et réunions | B14: 450000 | C14: 150000 | D14: 150000 | E14: 250000 | F14: 150000 | G14: 150000 | H14: =SUM(B14:G14) -> 1300000
A15: Formations et activités | B15: 0 | C15: 380000 | D15: 0 | E15: 0 | F15: 380000 | G15: 0 | H15: =SUM(B15:G15) -> 760000
A16: Fournitures | B16: 120000 | C16: 50000 | D16: 0 | E16: 80000 | F16: 40000 | G16: 40000 | H16: =SUM(B16:G16) -> 330000
A17: Transport et communication | B17: 80000 | C17: 60000 | D17: 60000 | E17: 60000 | F17: 60000 | G17: 60000 | H17: =SUM(B17:G17) -> 380000
A18: Total dépenses | B18: =SUM(B13:B17) -> 1400000 | C18: =SUM(C13:C17) -> 640000 | D18: =SUM(D13:D17) -> 210000 | E18: =SUM(E13:E17) -> 390000 | F18: =SUM(F13:F17) -> 630000 | G18: =SUM(G13:G17) -> 250000 | H18: =SUM(H13:H17) -> 3520000
A20: Résultat du mois | B20: =B10-B18 -> 150000 | C20: =C10-C18 -> 960000 | D20: =D10-D18 -> 1340000 | E20: =E10-E18 -> 1210000 | F20: =F10-F18 -> 1170000 | G20: =G10-G18 -> 1450000 | H20: =H10-H18 -> 6280000
A21: Solde de trésorerie en fin de mois | B21: =$B$4+B20 -> 5190000 | C21: =B21+C20 -> 6150000 | D21: =C21+D20 -> 7490000 | E21: =D21+E20 -> 8700000 | F21: =E21+F20 -> 9870000 | G21: =F21+G20 -> 11320000 | H21: =G21 -> 11320000

Sheet Recouvrement
A1: Taux de recouvrement des cotisations — S1 2026
A3: Cotisation mensuelle (GNF) | B3: 50000
A5: Mois | B5: Membres redevables | C5: Montant attendu | D5: Montant perçu | E5: Taux
A6: Janv. | B6: 36 | C6: =B6*$B$3 -> 1800000 | D6: ='Recettes et dépenses'!B8 -> 1350000 | E6: =IF(C6=0,0,D6/C6) -> 0.75
A7: Févr. | B7: 37 | C7: =B7*$B$3 -> 1850000 | D7: ='Recettes et dépenses'!C8 -> 1500000 | E7: =IF(C7=0,0,D7/C7) -> 0.81081081
A8: Mars | B8: 38 | C8: =B8*$B$3 -> 1900000 | D8: ='Recettes et dépenses'!D8 -> 1550000 | E8: =IF(C8=0,0,D8/C8) -> 0.81578947
A9: Avr. | B9: 39 | C9: =B9*$B$3 -> 1950000 | D9: ='Recettes et dépenses'!E8 -> 1500000 | E9: =IF(C9=0,0,D9/C9) -> 0.76923077
A10: Mai | B10: 40 | C10: =B10*$B$3 -> 2000000 | D10: ='Recettes et dépenses'!F8 -> 1600000 | E10: =IF(C10=0,0,D10/C10) -> 0.8
A11: Juin | B11: 41 | C11: =B11*$B$3 -> 2050000 | D11: ='Recettes et dépenses'!G8 -> 1600000 | E11: =IF(C11=0,0,D11/C11) -> 0.7804878
A12: Semestre | C12: =SUM(C6:C11) -> 11550000 | D12: =SUM(D6:D11) -> 9100000 | E12: =IF(C12=0,0,D12/C12) -> 0.78787879
A14: Membres redevables : membres actives au 1er du mois (hors suspendues et démissionnaires).
